agentic_patterns/__init__.py
agentic_patterns/multiagent_pattern/__init__.py
agentic_patterns/multiagent_pattern/agent.py
agentic_patterns/multiagent_pattern/crew.py
agentic_patterns/planning_pattern/__init__.py
agentic_patterns/planning_pattern/react_agent.py
agentic_patterns/reflection_pattern/__init__.py
agentic_patterns/reflection_pattern/reflection_agent.py
agentic_patterns/tool_pattern/__init__.py
agentic_patterns/tool_pattern/tool.py
agentic_patterns/tool_pattern/tool_agent.py
agentic_patterns/utils/__init__.py
agentic_patterns/utils/completions.py
agentic_patterns/utils/extraction.py
agentic_patterns/utils/logging.py
agentic_patterns-1.0.0.dist-info/LICENSE
agentic_patterns-1.0.0.dist-info/METADATA
agentic_patterns-1.0.0.dist-info/WHEEL
agentic_patterns-1.0.0.dist-info/RECORD
