Metadata-Version: 2.1
Name: agentic-patterns
Version: 1.0.0
Summary: 
License: MIT
Author: MichaelisTrofficus
Author-email: miguel.otero.pedrido.1993@gmail.com
Requires-Python: >=3.11,<4.0
Classifier: License :: OSI Approved :: MIT License
Classifier: Programming Language :: Python :: 3
Classifier: Programming Language :: Python :: 3.11
Classifier: Programming Language :: Python :: 3.12
Requires-Dist: colorama (>=0.4.6,<0.5.0)
Requires-Dist: graphviz (>=0.20.3,<0.21.0)
Requires-Dist: groq (>=0.9.0,<0.10.0)
Requires-Dist: jupyter (>=1.0.0,<2.0.0)
Requires-Dist: python-dotenv (>=1.0.1,<2.0.0)
Requires-Dist: types-colorama (>=0.4.15.20240311,<0.5.0.0)
